pycols/__init__.py
pycols-1.0.3.dist-info/LICENSE.txt
pycols-1.0.3.dist-info/METADATA
pycols-1.0.3.dist-info/WHEEL
pycols-1.0.3.dist-info/top_level.txt
pycols-1.0.3.dist-info/RECORD
