Metadata-Version: 2.1
Name: pycols
Version: 1.0.3
Summary: display colors in console
Author-email: Leander Kafemann <leander@kafemann.berlin>
Project-URL: Homepage, https://github.com/LeanderKafemann/pycols
Classifier: Programming Language :: Python :: 3
Classifier: License :: OSI Approved :: MIT License
Classifier: Operating System :: OS Independent
Requires-Python: >=3.11
License-File: LICENSE.txt
Requires-Dist: colorama
